MANIFEST.in
README.rst
paylogic_genres.json
setup.cfg
setup.py
paylogic_genres/.DS_Store
paylogic_genres/__init__.py
paylogic_genres/paylogic_genres.json
paylogic_genres/paylogic_genres.py
paylogic_genres.egg-info/PKG-INFO
paylogic_genres.egg-info/SOURCES.txt
paylogic_genres.egg-info/dependency_links.txt
paylogic_genres.egg-info/entry_points.txt
paylogic_genres.egg-info/requires.txt
paylogic_genres.egg-info/top_level.txt
paylogic_genres/locale/.DS_Store
paylogic_genres/locale/paylogic_genres.pot
paylogic_genres/locale/de/LC_MESSAGES/django.mo
paylogic_genres/locale/de/LC_MESSAGES/django.po
paylogic_genres/locale/en/.DS_Store
paylogic_genres/locale/en/LC_MESSAGES/django.mo
paylogic_genres/locale/en/LC_MESSAGES/django.po
paylogic_genres/locale/es/LC_MESSAGES/django.mo
paylogic_genres/locale/es/LC_MESSAGES/django.po
paylogic_genres/locale/fr/LC_MESSAGES/django.mo
paylogic_genres/locale/fr/LC_MESSAGES/django.po
paylogic_genres/locale/nl/LC_MESSAGES/django.mo
paylogic_genres/locale/nl/LC_MESSAGES/django.po
paylogic_genres/locale/pt/LC_MESSAGES/django.mo
paylogic_genres/locale/pt/LC_MESSAGES/django.po
paylogic_genres/locale/tr/LC_MESSAGES/django.mo
paylogic_genres/locale/tr/LC_MESSAGES/django.po