Metadata-Version: 1.1
Name: paylogic-genres
Version: 1.0.0
Summary: Genre classification used by Paylogic.
Home-page: https://github.com/paylogic/genres
Author: Paylogic
Author-email: UNKNOWN
License: MIT license
Platform: UNKNOWN
Classifier: Intended Audience :: Developers
Classifier: License :: OSI Approved :: MIT License
